tns/__init__.py
tns-1.0.0.dist-info/DESCRIPTION.rst
tns-1.0.0.dist-info/METADATA
tns-1.0.0.dist-info/RECORD
tns-1.0.0.dist-info/WHEEL
tns-1.0.0.dist-info/metadata.json
tns-1.0.0.dist-info/top_level.txt
