Metadata-Version: 2.0
Name: tns
Version: 1.0.0
Summary: Top News Selectors (tns): Top news parsing from select websites
Home-page: https://github.com/oduwsdl/top-news-selectors
Author: Grant Atkins
Author-email: gatkins@cs.odu.edu
License: MIT
Download-URL: https://github.com/oduwsdl/top-news-selectors
Keywords: html web tns odu memento
Platform: UNKNOWN
Classifier: Development Status :: 4 - Beta
Classifier: Programming Language :: Python :: 3
Classifier: License :: OSI Approved :: MIT License
Classifier: Intended Audience :: Developers
Classifier: Intended Audience :: Information Technology
Classifier: Intended Audience :: Science/Research
Classifier: Topic :: Text Processing :: Markup :: HTML
Provides: tns
Requires-Dist: beautifulsoup4
